galapagos/__init__.py
galapagos/genepool.py
galapagos/generation.py
galapagos/genotype.py
galapagos/individual.py
galapagos/locus.py
galapagos/simulation.py
galapagos/utils.py
galapagos_evo-0.1.1.dist-info/licenses/LICENSE
galapagos_evo-0.1.1.dist-info/METADATA
galapagos_evo-0.1.1.dist-info/WHEEL
galapagos_evo-0.1.1.dist-info/top_level.txt
galapagos_evo-0.1.1.dist-info/RECORD
