Metadata-Version: 2.4
Name: galapagos-evo
Version: 0.1.1
Summary: A small didatic package for evolution simulations
Author-email: Luan Leal <luanleal@usp.br>, Micael Baruch <micael.mbaruch@usp.br>
License-Expression: GPL-3.0-or-later
Project-URL: Homepage, https://github.com/thefire888/galapagos
Project-URL: Issues, https://github.com/thefire888/galapagos/issues
Classifier: Programming Language :: Python :: 3
Classifier: Operating System :: OS Independent
Requires-Python: >=3.12
License-File: LICENSE
Dynamic: license-file
